{
	"format_version": "1.21.6",
	"credit": "Made with Blockbench",
	"textures": {
		"0": "snc:custom/painting/armor",
		"particle": "snc:custom/painting/armor"
	},
	"elements": [
		{
			"from": [3, 2, 7.75],
			"to": [13, 12, 8.25],
			"rotation": {"angle": 0, "axis": "y", "origin": [5, 2, 7.75]},
			"faces": {
				"north": {"uv": [0, 0, 16, 16], "texture": "#0"},
				"east": {"uv": [0, 0, 0.5, 16], "texture": "#0"},
				"south": {"uv": [0, 0, 16, 16], "texture": "#0"},
				"west": {"uv": [15.5, 0, 16, 16], "texture": "#0"},
				"up": {"uv": [0, 0, 16, 0.5], "texture": "#0"},
				"down": {"uv": [0, 15.5, 16, 16], "texture": "#0"}
			}
		}
	]
}